datajuggler/__init__.py
datajuggler/checkdigit.py
datajuggler/core.py
datajuggler/dicthelper.py
datajuggler/keys.py
datajuggler/strings.py
datajuggler/utils.py
datajuggler/validator.py
datajuggler/versions.py
datajuggler/serializer/__init__.py
datajuggler/serializer/abstract.py
datajuggler/serializer/base64.py
datajuggler/serializer/class_serializer.py
datajuggler/serializer/cloudpickle.py
datajuggler/serializer/core.py
datajuggler/serializer/csv.py
datajuggler/serializer/ini.py
datajuggler/serializer/json.py
datajuggler/serializer/msgpack.py
datajuggler/serializer/plist.py
datajuggler/serializer/query_string.py
datajuggler/serializer/toml.py
datajuggler/serializer/xml.py
datajuggler/serializer/yaml.py
datajuggler-0.5.5.dist-info/LICENSE
datajuggler-0.5.5.dist-info/METADATA
datajuggler-0.5.5.dist-info/WHEEL
datajuggler-0.5.5.dist-info/top_level.txt
datajuggler-0.5.5.dist-info/RECORD
