Metadata-Version: 2.1
Name: datajuggler
Version: 0.5.5
Summary: Utility for data juggling.
Home-page: https://github.com/iisaka51/datajuggler
Author: Goichi (Iisaka) Yukawa
Author-email: iisaka51@gmail.com
License: MIT
Platform: UNKNOWN
Classifier: License :: OSI Approved :: MIT License
Classifier: Programming Language :: Python :: 3.8
Classifier: Programming Language :: Python :: 3.9
Classifier: Programming Language :: Python :: 3.10
License-File: LICENSE
Requires-Dist: multimethod (>=1.8)
Requires-Dist: Serialize (>=0.2.1)
Requires-Dist: cryptography (>=36.0.0)
Provides-Extra: bson
Requires-Dist: bson (>=0.3.5.1) ; extra == 'bson'
Provides-Extra: cloudpack
Requires-Dist: cloudpickle (>=2.2.0) ; extra == 'cloudpack'
Provides-Extra: database
Requires-Dist: dataset (>=1.5.0) ; extra == 'database'
Provides-Extra: dill
Requires-Dist: dill (>=0.5.10) ; extra == 'dill'
Provides-Extra: emoji
Requires-Dist: emoji (==2.1.0) ; extra == 'emoji'
Provides-Extra: msgpack
Requires-Dist: msgpack (>=1.0.4) ; extra == 'msgpack'
Provides-Extra: pandas
Requires-Dist: pandas (>=1.4.0) ; extra == 'pandas'
Provides-Extra: phpserialize
Requires-Dist: phpserialize (>=1.3) ; extra == 'phpserialize'
Provides-Extra: requests
Requires-Dist: requests (>=2.27.0) ; extra == 'requests'
Provides-Extra: serializer
Requires-Dist: bson (>=0.3.5.1) ; extra == 'serializer'
Requires-Dist: dill (>=6.0) ; extra == 'serializer'
Requires-Dist: PyYAML (>=6.0) ; extra == 'serializer'
Requires-Dist: msgpack (>-1.0.4) ; extra == 'serializer'
Requires-Dist: phpserialize (>=1.3) ; extra == 'serializer'
Requires-Dist: serpent (>=1.4.1) ; extra == 'serializer'
Requires-Dist: toml (>=0.10.2) ; extra == 'serializer'
Requires-Dist: xmltodict (>=0.13.0) ; extra == 'serializer'
Requires-Dist: cloudpickle (>=2.2.0) ; extra == 'serializer'
Provides-Extra: serpent
Requires-Dist: serpent (>=1.4.1) ; extra == 'serpent'
Provides-Extra: toml
Requires-Dist: toml (>=0.10.2) ; extra == 'toml'
Provides-Extra: xml
Requires-Dist: xmltodict (>=0.13.0) ; extra == 'xml'
Provides-Extra: yaml
Requires-Dist: PyYAML (>=6.0) ; extra == 'yaml'
